{"_id":{"$oid":"5cd04d3eef3c0a80a40c600f"},"email":"hasan@gmail.com","uname":"Navod Janitha","password":"jdhdgdud6272o,","__v":{"$numberInt":"0"}}
{"_id":{"$oid":"5cd162fe937845444026f485"},"email":"kamal@gmail.com","password":"hdsvs578G","__v":{"$numberInt":"0"}}
{"_id":{"$oid":"5cd163a5937845444026f486"},"email":"d@gmail.com","uname":"Danuka","password":"12453242jdg","__v":{"$numberInt":"0"}}
{"_id":{"$oid":"5cdb94ac0c6e5069f4e56c4e"},"email":"ish@gmail.com","uname":"Isuru","password":"navhgf32427@","__v":{"$numberInt":"0"}}
{"_id":{"$oid":"5cdb978f0df49c88b0d1e8d1"},"email":"dinuka@gmail.com","uname":"dinuka","password":"asd","__v":{"$numberInt":"0"}}
{"_id":{"$oid":"5cdbc50e5d024b95e8332c6a"},"email":"janitha.navod@gmail.com","uname":"Navod Janitha","password":"12345678","__v":{"$numberInt":"0"}}
